---
title: 00-Javaæ•°ç»„éå†æ€§èƒ½å¯¹æ¯”
date: 2024-9-13 21:15:36
tags: JavaåŸºç¡€
categories: JavaåŸºç¡€
toc: true
language: zh-CN
---

## ä¸‰ç§éå†æ–¹å¼æ€§èƒ½å¯¹æ¯”

1. å¾ªç¯ä¸æ•°ç»„çš„`length`æ¯”è¾ƒ
```java
public class JavaMain {
    static Object[] objs = new Object[10000000];
    static int zero() {
        int sum = 0;
        for(int i = 0; i < objs.length; i++) {
            sum ^= objs[i].hashCode();
        }
        return sum;
    }
}
```

2. å°†æ•°ç»„`length`å­˜åœ¨æ–¹æ³•æ ˆä¸­

```java
public class JavaMain {
    static Object[] objs = new Object[10000000];
    static int one() {
        int sum = 0;
        int len = objs.length;
        for(int i = 0; i < len; i++) {
            sum ^= objs[i].hashCode();
        }
        return sum;
    }
}
```

3. for-eachå¾ªç¯

```java
public class JavaMain {
    static Object[] objs = new Object[10000000];
    static int two() {
        int sum = 0;
        for (Object obj : objs) {
            sum ^= obj.hashCode();
        }
        return sum;
    }
}
```

### æµ‹è¯•é€Ÿåº¦
```java
public class JavaMain {
    static Object[] objs = new Object[10000000];
    static long run(IntSupplier f) {
        long start = System.currentTimeMillis();
        int result = 0;
        for(int i = 0; i < 100; i++) {
            result = f.getAsInt();
        }
        long end = System.currentTimeMillis();
        System.out.println("result = " + result + ", time = " + (end - start) / 1000.0);
        return  end - start;
    }
    public static void main(String[] args) {
        for (int i = 0; i < objs.length; i++) {
            objs[i] = new Object();
            objs[i].hashCode(); // é¦–æ¬¡è®¡ç®—hashcodeæ›´æ…¢ï¼Œå…ˆç¼“å­˜
        }
        for (int i = 0; i < 10; i++) {
            long zeroTime = run(JavaMain::zero);
            long oneTime = run(JavaMain::one);
            long twoTime = run(JavaMain::two);
            System.out.printf("2æ¯”1å¿«: %.2f%%\n", ((double)oneTime - twoTime) / oneTime * 100);
            System.out.printf("2æ¯”0å¿«: %.2f%%\n", ((double)zeroTime - twoTime) / zeroTime * 100);
            System.out.printf("1æ¯”0å¿«: %.2f%%\n", ((double)zeroTime - oneTime) / oneTime * 100);
        }
    }
}
```

### æµ‹è¯•ç»“æœ

```text
result = 360970567, time = 1.393
result = 360970567, time = 1.174
result = 360970567, time = 0.886
2æ¯”1å¿«: 24.53%
2æ¯”0å¿«: 36.40%
1æ¯”0å¿«: 18.65%
```

## å¯¹æ¯”å­—èŠ‚ç 

ä½¿ç”¨`javap -c`æŸ¥çœ‹å­—èŠ‚ğŸ´

```bytecode
static int zero();
Code:
    0: iconst_0
    1: istore_0
    2: iconst_0
    3: istore_1
    4: iload_1
    5: getstatic     #7                  // Field objs:[Ljava/lang/Object;
    8: arraylength
    9: if_icmpge     29
    12: iload_0
    13: getstatic     #7                  // Field objs:[Ljava/lang/Object;
    16: iload_1
    17: aaload
    18: invokevirtual #13                 // Method java/lang/Object.hashCode:()I
    21: ixor
    22: istore_0
    23: iinc          1, 1
    26: goto          4
    29: iload_0
    30: ireturn
```

- æ•°ç»„çš„`length`å¹¶ä¸æ˜¯ä¸€ä¸ªå­—æ®µï¼Œæ²¡æœ‰é€šè¿‡`getfield`è·å–

```bytecode
static int one();
Code:
    0: iconst_0
    1: istore_0
    2: getstatic     #7                  // Field objs:[Ljava/lang/Object;
    5: arraylength
    6: istore_1
    7: iconst_0
    8: istore_2
    9: iload_2
    10: iload_1
    11: if_icmpge     31
    14: iload_0
    15: getstatic     #7                  // Field objs:[Ljava/lang/Object;
    18: iload_2
    19: aaload
    20: invokevirtual #13                 // Method java/lang/Object.hashCode:()I
    23: ixor
    24: istore_0
    25: iinc          2, 1
    28: goto          9
    31: iload_0
    32: ireturn
```

- æ¯æ¬¡ä½¿ç”¨`arraylength`è·å–æ•°ç»„é•¿åº¦ä¼šæ›´æ…¢ï¼Œå…·ä½“`arraylength`åšäº†ä»€ä¹ˆå¯ä»¥çœ‹è¿™ç¯‡æ–‡ç« [JVMæ˜¯å¦‚ä½•å¾—åˆ°æ•°ç»„é•¿åº¦çš„](https://blog.csdn.net/scjava/article/details/108219216)
- `zero`å’Œ`one`å¯¹æ¯”
  - `zero`æ¯æ¬¡å¾ªç¯å‰ï¼Œè¦ä¾æ¬¡æ‰§è¡Œ`iload_1`, `getstatic`, `arraylength`, `if_icmpge`
  - `one`æ¯æ¬¡å¾ªç¯å‰ï¼Œè¦ä¾æ¬¡æ‰§è¡Œ`iload_2`, `iload_1`, `if_icmpge`
  - `one`åªéœ€è¦è™šæ‹Ÿæœºè¯»å–ä¸¤ä¸ªæ“ä½œæ•°è¿›è¡Œæ¯”è¾ƒå°±å¯ä»¥ï¼Œè€Œ`zero`éœ€è¦é€šè¿‡`getstatic`è·å–æ•°ç»„å¯¹è±¡ï¼Œ`arraylength`è·å–é•¿åº¦

```bytecode
static int two();
Code:
    0: iconst_0
    1: istore_0
    2: getstatic     #7                  // Field objs:[Ljava/lang/Object;
    5: astore_1
    6: aload_1
    7: arraylength
    8: istore_2
    9: iconst_0
    10: istore_3
    11: iload_3
    12: iload_2
    13: if_icmpge     35
    16: aload_1
    17: iload_3
    18: aaload
    19: astore        4
    21: iload_0
    22: aload         4
    24: invokevirtual #13                 // Method java/lang/Object.hashCode:()I
    27: ixor
    28: istore_0
    29: iinc          3, 1
    32: goto          11
    35: iload_0
    36: ireturn
```

- `one`å’Œ`two`å¯¹æ¯”
  - åœ¨å¾ªç¯å‰ï¼Œä¸¤è€…éƒ½æ˜¯é€šè¿‡`iload`è¯»å–æ•°ç»„é•¿åº¦å’Œå½“å‰indexå¯¹æ¯”
  - åœ¨å¾ªç¯ä½“ä¸­
    - `one`æ¯æ¬¡éœ€è¦`getstatic`è·å–æ•°ç»„å¯¹è±¡ï¼Œç„¶åæ ¹æ®åç§»é‡å–å‡ºå¯¹åº”ä½ç½®çš„å¯¹è±¡
    - `two`åœ¨å¾ªç¯å¼€å§‹å‰ï¼Œå°±å°†æ•°ç»„å¯¹è±¡å­˜åœ¨æœ¬åœ°æ–¹æ³•æ ˆä¸­ï¼Œä¸éœ€è¦ä½¿ç”¨`getstatic`æ¥è·å–æ•°ç»„å¯¹è±¡

> å¼ºçƒˆæ€€ç–‘æ˜¯`getstatic`æ€§èƒ½è¿‡äºæ‹‰èƒ¯ï¼Œå¯¼è‡´ä¸‰è€…å¾ªç¯é€Ÿåº¦å·®å¼‚å¤§

## å°†æ•°ç»„å¯¹è±¡ä½œä¸ºå‚æ•°ä¼ é€’åˆ°å‡½æ•°ä¸­

### æµ‹è¯•ä»£ç 

```java
public class JavaMain {
    static Object[] objs = new Object[10000000];
    static int zero(Object[] objs) {
        int sum = 0;
        for(int i = 0; i < objs.length; i++) {
            sum ^= objs[i].hashCode();
        }
        return sum;
    }
    static int one(Object[] objs) {
        int sum = 0;
        int len = objs.length;
        for(int i = 0; i < len; i++) {
            sum ^= objs[i].hashCode();
        }
        return sum;
    }
    static int two(Object[] objs) {
        int sum = 0;
        for (Object obj : objs) {
            sum ^= obj.hashCode();
        }
        return sum;
    }
    static long run(Function<Object[], Integer> f) {
        long start = System.currentTimeMillis();
        int result = 0;
        for(int i = 0; i < 100; i++) {
            result = f.apply(objs);
        }
        long end = System.currentTimeMillis();
        System.out.println("result = " + result + ", time = " + (end - start) / 1000.0);
        return  end - start;
    }
    public static void main(String[] args) {
        for (int i = 0; i < objs.length; i++) {
            objs[i] = new Object();
            objs[i].hashCode();
        }
        for (int i = 0; i < 10; i++) {
            long zeroTime = run(JavaMain::zero);
            long oneTime = run(JavaMain::one);
            long twoTime = run(JavaMain::two);
            System.out.printf("2æ¯”1å¿«: %.2f%%\n", ((double)oneTime - twoTime) / oneTime * 100);
            System.out.printf("2æ¯”0å¿«: %.2f%%\n", ((double)zeroTime - twoTime) / zeroTime * 100);
            System.out.printf("1æ¯”0å¿«: %.2f%%\n", ((double)zeroTime - oneTime) / oneTime * 100);
        }
    }
}
```

### æ¯”è¾ƒç»“æœ
```text
result = 360970567, time = 0.85
result = 360970567, time = 0.871
result = 360970567, time = 0.873
2æ¯”1å¿«: -0.23%
2æ¯”0å¿«: -2.71%
1æ¯”0å¿«: -2.41%
result = 360970567, time = 0.864
result = 360970567, time = 0.847
result = 360970567, time = 0.849
2æ¯”1å¿«: -0.24%
2æ¯”0å¿«: 1.74%
1æ¯”0å¿«: 2.01%
result = 360970567, time = 0.851
result = 360970567, time = 0.849
result = 360970567, time = 0.862
2æ¯”1å¿«: -1.53%
2æ¯”0å¿«: -1.29%
1æ¯”0å¿«: 0.24%
```

> ä¸‰ç§æ–¹æ³•éš¾åˆ†ä¼¯ä»²

### å­—èŠ‚ç å¯¹æ¯”

```bytecode
Compiled from "JavaMain.java"
public class test.JavaMain {
  static java.lang.Object[] objs;

  public test.JavaMain();
    Code:
       0: aload_0
       1: invokespecial #1                  // Method java/lang/Object."<init>":()V
       4: return

  static int zero(java.lang.Object[]);
    Code:
       0: iconst_0
       1: istore_1
       2: iconst_0
       3: istore_2
       4: iload_2
       5: aload_0
       6: arraylength
       7: if_icmpge     25
      10: iload_1
      11: aload_0
      12: iload_2
      13: aaload
      14: invokevirtual #7                  // Method java/lang/Object.hashCode:()I
      17: ixor
      18: istore_1
      19: iinc          2, 1
      22: goto          4
      25: iload_1
      26: ireturn

  static int one(java.lang.Object[]);
    Code:
       0: iconst_0
       1: istore_1
       2: aload_0
       3: arraylength
       4: istore_2
       5: iconst_0
       6: istore_3
       7: iload_3
       8: iload_2
       9: if_icmpge     27
      12: iload_1
      13: aload_0
      14: iload_3
      15: aaload
      16: invokevirtual #7                  // Method java/lang/Object.hashCode:()I
      19: ixor
      20: istore_1
      21: iinc          3, 1
      24: goto          7
      27: iload_1
      28: ireturn

  static int two(java.lang.Object[]);
    Code:
       0: iconst_0
       1: istore_1
       2: aload_0
       3: astore_2
       4: aload_2
       5: arraylength
       6: istore_3
       7: iconst_0
       8: istore        4
      10: iload         4
      12: iload_3
      13: if_icmpge     36
      16: aload_2
      17: iload         4
      19: aaload
      20: astore        5
      22: iload_1
      23: aload         5
      25: invokevirtual #7                  // Method java/lang/Object.hashCode:()I
      28: ixor
      29: istore_1
      30: iinc          4, 1
      33: goto          10
      36: iload_1
      37: ireturn

  static {};
    Code:
       0: ldc           #77                 // int 10000000
       2: anewarray     #2                  // class java/lang/Object
       5: putstatic     #17                 // Field objs:[Ljava/lang/Object;
       8: return
}
```

> ä¸‰è€…åŒºåˆ«ä¸å¤§ï¼Œæ€»ä½“è€—æ—¶åŒºåˆ«ä¹Ÿä¸å¤§ï¼Œå¯è§`arraylength`æŒ‡ä»¤å¹¶ä¸æ˜¯æ€§èƒ½ç“¶é¢ˆï¼Œè€Œæ˜¯`getstatic`æœ‰è¾ƒå¤§å½±å“
> åŒæ ·ï¼Œæˆ‘ä¹Ÿæµ‹è¯•äº†ä¸é€šè¿‡å‡½æ•°å‚æ•°ä¼ é€’ï¼Œè€Œå°†æ•°ç»„å’Œä¸‰ä¸ªæ–¹æ³•æ”¹æˆé`static`ä¿®é¥°çš„ï¼Œä¸‰è€…å·®å¼‚è¾ƒå¤§ï¼Œå¯è§`getField`æŒ‡ä»¤çš„æ€§èƒ½å¼€é”€ä¹Ÿè¦æ¯”`load`å¤§

## ç»“è®º
åœ¨éå†æ•°ç»„æ—¶ï¼Œä¸è®ºæ˜¯ä½¿ç”¨æ•°ç»„çš„`length`ï¼Œæå‰å­˜å‚¨æ•°ç»„é•¿åº¦ï¼Œè¿˜æ˜¯ä½¿ç”¨`for-each`ï¼Œå·®åˆ«ä¸å¤§ï¼Œé‡è¦çš„æ˜¯å…ˆå°†æ•°ç»„å¯¹è±¡æ”¾åˆ°æœ¬åœ°æ–¹æ³•æ ˆï¼Œé¿å…é¢‘ç¹æ‰§è¡Œ`getstatic`å’Œ`getfield`æŒ‡ä»¤ï¼Œé€ æˆæ€§èƒ½å½±å“ã€‚

å’Œå…«è‚¡[å®‰å“æ€§èƒ½ä¼˜åŒ–](https://github.com/francistao/LearningNotes/blob/master/Part1/Android/Android%E6%80%A7%E8%83%BD%E4%BC%98%E5%8C%96.md)æ‰€å½’å’çš„åŸå› ç¨æœ‰ä¸åŒã€‚